[
  {
    "id": "iit-jee-main-physics-medium-fill_blank-001",
    "question": "Fill in the blank: distance travelled per unit time. The term is ____.",
    "options": [],
    "answer": "speed",
    "explanation": "Speed means distance travelled per unit time.",
    "level": "iit-jee-main",
    "subject": "physics",
    "difficulty": "medium",
    "type": "fill_blank"
  },
  {
    "id": "iit-jee-main-physics-medium-fill_blank-002",
    "question": "The correct term for 'speed with direction' is ____.",
    "options": [],
    "answer": "velocity",
    "explanation": "Velocity means speed with direction.",
    "level": "iit-jee-main",
    "subject": "physics",
    "difficulty": "medium",
    "type": "fill_blank"
  },
  {
    "id": "iit-jee-main-physics-medium-fill_blank-003",
    "question": "____ means rate of change of velocity.",
    "options": [],
    "answer": "acceleration",
    "explanation": "Acceleration means rate of change of velocity.",
    "level": "iit-jee-main",
    "subject": "physics",
    "difficulty": "medium",
    "type": "fill_blank"
  },
  {
    "id": "iit-jee-main-physics-medium-fill_blank-004",
    "question": "Fill in the blank: a push or pull that can change motion. The term is ____.",
    "options": [],
    "answer": "force",
    "explanation": "Force means a push or pull that can change motion.",
    "level": "iit-jee-main",
    "subject": "physics",
    "difficulty": "medium",
    "type": "fill_blank"
  },
  {
    "id": "iit-jee-main-physics-medium-fill_blank-005",
    "question": "The correct term for 'force multiplied by displacement in the direction of force' is ____.",
    "options": [],
    "answer": "work",
    "explanation": "Work means force multiplied by displacement in the direction of force.",
    "level": "iit-jee-main",
    "subject": "physics",
    "difficulty": "medium",
    "type": "fill_blank"
  },
  {
    "id": "iit-jee-main-physics-medium-fill_blank-006",
    "question": "____ means rate of doing work.",
    "options": [],
    "answer": "power",
    "explanation": "Power means rate of doing work.",
    "level": "iit-jee-main",
    "subject": "physics",
    "difficulty": "medium",
    "type": "fill_blank"
  },
  {
    "id": "iit-jee-main-physics-medium-fill_blank-007",
    "question": "Fill in the blank: mass multiplied by velocity. The term is ____.",
    "options": [],
    "answer": "momentum",
    "explanation": "Momentum means mass multiplied by velocity.",
    "level": "iit-jee-main",
    "subject": "physics",
    "difficulty": "medium",
    "type": "fill_blank"
  },
  {
    "id": "iit-jee-main-physics-medium-fill_blank-008",
    "question": "The correct term for 'the force of attraction between masses' is ____.",
    "options": [],
    "answer": "gravity",
    "explanation": "Gravity means the force of attraction between masses.",
    "level": "iit-jee-main",
    "subject": "physics",
    "difficulty": "medium",
    "type": "fill_blank"
  },
  {
    "id": "iit-jee-main-physics-medium-fill_blank-009",
    "question": "____ means a force that opposes motion between surfaces.",
    "options": [],
    "answer": "friction",
    "explanation": "Friction means a force that opposes motion between surfaces.",
    "level": "iit-jee-main",
    "subject": "physics",
    "difficulty": "medium",
    "type": "fill_blank"
  },
  {
    "id": "iit-jee-main-physics-medium-fill_blank-010",
    "question": "Fill in the blank: force per unit area. The term is ____.",
    "options": [],
    "answer": "pressure",
    "explanation": "Pressure means force per unit area.",
    "level": "iit-jee-main",
    "subject": "physics",
    "difficulty": "medium",
    "type": "fill_blank"
  },
  {
    "id": "iit-jee-main-physics-medium-fill_blank-011",
    "question": "The correct term for 'mass per unit volume' is ____.",
    "options": [],
    "answer": "density",
    "explanation": "Density means mass per unit volume.",
    "level": "iit-jee-main",
    "subject": "physics",
    "difficulty": "medium",
    "type": "fill_blank"
  },
  {
    "id": "iit-jee-main-physics-medium-fill_blank-012",
    "question": "____ means the capacity to do work.",
    "options": [],
    "answer": "energy",
    "explanation": "Energy means the capacity to do work.",
    "level": "iit-jee-main",
    "subject": "physics",
    "difficulty": "medium",
    "type": "fill_blank"
  },
  {
    "id": "iit-jee-main-physics-medium-fill_blank-013",
    "question": "Fill in the blank: energy transferred because of temperature difference. The term is ____.",
    "options": [],
    "answer": "heat",
    "explanation": "Heat means energy transferred because of temperature difference.",
    "level": "iit-jee-main",
    "subject": "physics",
    "difficulty": "medium",
    "type": "fill_blank"
  },
  {
    "id": "iit-jee-main-physics-medium-fill_blank-014",
    "question": "The correct term for 'a measure of hotness or coldness' is ____.",
    "options": [],
    "answer": "temperature",
    "explanation": "Temperature means a measure of hotness or coldness.",
    "level": "iit-jee-main",
    "subject": "physics",
    "difficulty": "medium",
    "type": "fill_blank"
  },
  {
    "id": "iit-jee-main-physics-medium-fill_blank-015",
    "question": "____ means a form of energy produced by vibrating objects.",
    "options": [],
    "answer": "sound",
    "explanation": "Sound means a form of energy produced by vibrating objects.",
    "level": "iit-jee-main",
    "subject": "physics",
    "difficulty": "medium",
    "type": "fill_blank"
  },
  {
    "id": "iit-jee-main-physics-medium-fill_blank-016",
    "question": "Fill in the blank: a form of electromagnetic radiation visible to the eye. The term is ____.",
    "options": [],
    "answer": "light",
    "explanation": "Light means a form of electromagnetic radiation visible to the eye.",
    "level": "iit-jee-main",
    "subject": "physics",
    "difficulty": "medium",
    "type": "fill_blank"
  },
  {
    "id": "iit-jee-main-physics-medium-fill_blank-017",
    "question": "The correct term for 'a disturbance that transfers energy' is ____.",
    "options": [],
    "answer": "wave",
    "explanation": "Wave means a disturbance that transfers energy.",
    "level": "iit-jee-main",
    "subject": "physics",
    "difficulty": "medium",
    "type": "fill_blank"
  },
  {
    "id": "iit-jee-main-physics-medium-fill_blank-018",
    "question": "____ means bouncing back of light from a surface.",
    "options": [],
    "answer": "reflection",
    "explanation": "Reflection means bouncing back of light from a surface.",
    "level": "iit-jee-main",
    "subject": "physics",
    "difficulty": "medium",
    "type": "fill_blank"
  },
  {
    "id": "iit-jee-main-physics-medium-fill_blank-019",
    "question": "Fill in the blank: bending of light when it enters a new medium. The term is ____.",
    "options": [],
    "answer": "refraction",
    "explanation": "Refraction means bending of light when it enters a new medium.",
    "level": "iit-jee-main",
    "subject": "physics",
    "difficulty": "medium",
    "type": "fill_blank"
  },
  {
    "id": "iit-jee-main-physics-medium-fill_blank-020",
    "question": "The correct term for 'a transparent optical device that refracts light' is ____.",
    "options": [],
    "answer": "lens",
    "explanation": "Lens means a transparent optical device that refracts light.",
    "level": "iit-jee-main",
    "subject": "physics",
    "difficulty": "medium",
    "type": "fill_blank"
  },
  {
    "id": "iit-jee-main-physics-medium-fill_blank-021",
    "question": "____ means distance travelled per unit time.",
    "options": [],
    "answer": "speed",
    "explanation": "Speed means distance travelled per unit time.",
    "level": "iit-jee-main",
    "subject": "physics",
    "difficulty": "medium",
    "type": "fill_blank"
  },
  {
    "id": "iit-jee-main-physics-medium-fill_blank-022",
    "question": "Fill in the blank: speed with direction. The term is ____.",
    "options": [],
    "answer": "velocity",
    "explanation": "Velocity means speed with direction.",
    "level": "iit-jee-main",
    "subject": "physics",
    "difficulty": "medium",
    "type": "fill_blank"
  },
  {
    "id": "iit-jee-main-physics-medium-fill_blank-023",
    "question": "The correct term for 'rate of change of velocity' is ____.",
    "options": [],
    "answer": "acceleration",
    "explanation": "Acceleration means rate of change of velocity.",
    "level": "iit-jee-main",
    "subject": "physics",
    "difficulty": "medium",
    "type": "fill_blank"
  },
  {
    "id": "iit-jee-main-physics-medium-fill_blank-024",
    "question": "____ means a push or pull that can change motion.",
    "options": [],
    "answer": "force",
    "explanation": "Force means a push or pull that can change motion.",
    "level": "iit-jee-main",
    "subject": "physics",
    "difficulty": "medium",
    "type": "fill_blank"
  },
  {
    "id": "iit-jee-main-physics-medium-fill_blank-025",
    "question": "Fill in the blank: force multiplied by displacement in the direction of force. The term is ____.",
    "options": [],
    "answer": "work",
    "explanation": "Work means force multiplied by displacement in the direction of force.",
    "level": "iit-jee-main",
    "subject": "physics",
    "difficulty": "medium",
    "type": "fill_blank"
  },
  {
    "id": "iit-jee-main-physics-medium-fill_blank-026",
    "question": "The correct term for 'rate of doing work' is ____.",
    "options": [],
    "answer": "power",
    "explanation": "Power means rate of doing work.",
    "level": "iit-jee-main",
    "subject": "physics",
    "difficulty": "medium",
    "type": "fill_blank"
  },
  {
    "id": "iit-jee-main-physics-medium-fill_blank-027",
    "question": "____ means mass multiplied by velocity.",
    "options": [],
    "answer": "momentum",
    "explanation": "Momentum means mass multiplied by velocity.",
    "level": "iit-jee-main",
    "subject": "physics",
    "difficulty": "medium",
    "type": "fill_blank"
  },
  {
    "id": "iit-jee-main-physics-medium-fill_blank-028",
    "question": "Fill in the blank: the force of attraction between masses. The term is ____.",
    "options": [],
    "answer": "gravity",
    "explanation": "Gravity means the force of attraction between masses.",
    "level": "iit-jee-main",
    "subject": "physics",
    "difficulty": "medium",
    "type": "fill_blank"
  },
  {
    "id": "iit-jee-main-physics-medium-fill_blank-029",
    "question": "The correct term for 'a force that opposes motion between surfaces' is ____.",
    "options": [],
    "answer": "friction",
    "explanation": "Friction means a force that opposes motion between surfaces.",
    "level": "iit-jee-main",
    "subject": "physics",
    "difficulty": "medium",
    "type": "fill_blank"
  },
  {
    "id": "iit-jee-main-physics-medium-fill_blank-030",
    "question": "____ means force per unit area.",
    "options": [],
    "answer": "pressure",
    "explanation": "Pressure means force per unit area.",
    "level": "iit-jee-main",
    "subject": "physics",
    "difficulty": "medium",
    "type": "fill_blank"
  },
  {
    "id": "iit-jee-main-physics-medium-fill_blank-031",
    "question": "Fill in the blank: mass per unit volume. The term is ____.",
    "options": [],
    "answer": "density",
    "explanation": "Density means mass per unit volume.",
    "level": "iit-jee-main",
    "subject": "physics",
    "difficulty": "medium",
    "type": "fill_blank"
  },
  {
    "id": "iit-jee-main-physics-medium-fill_blank-032",
    "question": "The correct term for 'the capacity to do work' is ____.",
    "options": [],
    "answer": "energy",
    "explanation": "Energy means the capacity to do work.",
    "level": "iit-jee-main",
    "subject": "physics",
    "difficulty": "medium",
    "type": "fill_blank"
  },
  {
    "id": "iit-jee-main-physics-medium-fill_blank-033",
    "question": "____ means energy transferred because of temperature difference.",
    "options": [],
    "answer": "heat",
    "explanation": "Heat means energy transferred because of temperature difference.",
    "level": "iit-jee-main",
    "subject": "physics",
    "difficulty": "medium",
    "type": "fill_blank"
  },
  {
    "id": "iit-jee-main-physics-medium-fill_blank-034",
    "question": "Fill in the blank: a measure of hotness or coldness. The term is ____.",
    "options": [],
    "answer": "temperature",
    "explanation": "Temperature means a measure of hotness or coldness.",
    "level": "iit-jee-main",
    "subject": "physics",
    "difficulty": "medium",
    "type": "fill_blank"
  },
  {
    "id": "iit-jee-main-physics-medium-fill_blank-035",
    "question": "The correct term for 'a form of energy produced by vibrating objects' is ____.",
    "options": [],
    "answer": "sound",
    "explanation": "Sound means a form of energy produced by vibrating objects.",
    "level": "iit-jee-main",
    "subject": "physics",
    "difficulty": "medium",
    "type": "fill_blank"
  },
  {
    "id": "iit-jee-main-physics-medium-fill_blank-036",
    "question": "____ means a form of electromagnetic radiation visible to the eye.",
    "options": [],
    "answer": "light",
    "explanation": "Light means a form of electromagnetic radiation visible to the eye.",
    "level": "iit-jee-main",
    "subject": "physics",
    "difficulty": "medium",
    "type": "fill_blank"
  },
  {
    "id": "iit-jee-main-physics-medium-fill_blank-037",
    "question": "Fill in the blank: a disturbance that transfers energy. The term is ____.",
    "options": [],
    "answer": "wave",
    "explanation": "Wave means a disturbance that transfers energy.",
    "level": "iit-jee-main",
    "subject": "physics",
    "difficulty": "medium",
    "type": "fill_blank"
  },
  {
    "id": "iit-jee-main-physics-medium-fill_blank-038",
    "question": "The correct term for 'bouncing back of light from a surface' is ____.",
    "options": [],
    "answer": "reflection",
    "explanation": "Reflection means bouncing back of light from a surface.",
    "level": "iit-jee-main",
    "subject": "physics",
    "difficulty": "medium",
    "type": "fill_blank"
  },
  {
    "id": "iit-jee-main-physics-medium-fill_blank-039",
    "question": "____ means bending of light when it enters a new medium.",
    "options": [],
    "answer": "refraction",
    "explanation": "Refraction means bending of light when it enters a new medium.",
    "level": "iit-jee-main",
    "subject": "physics",
    "difficulty": "medium",
    "type": "fill_blank"
  },
  {
    "id": "iit-jee-main-physics-medium-fill_blank-040",
    "question": "Fill in the blank: a transparent optical device that refracts light. The term is ____.",
    "options": [],
    "answer": "lens",
    "explanation": "Lens means a transparent optical device that refracts light.",
    "level": "iit-jee-main",
    "subject": "physics",
    "difficulty": "medium",
    "type": "fill_blank"
  },
  {
    "id": "iit-jee-main-physics-medium-fill_blank-041",
    "question": "The correct term for 'distance travelled per unit time' is ____.",
    "options": [],
    "answer": "speed",
    "explanation": "Speed means distance travelled per unit time.",
    "level": "iit-jee-main",
    "subject": "physics",
    "difficulty": "medium",
    "type": "fill_blank"
  },
  {
    "id": "iit-jee-main-physics-medium-fill_blank-042",
    "question": "____ means speed with direction.",
    "options": [],
    "answer": "velocity",
    "explanation": "Velocity means speed with direction.",
    "level": "iit-jee-main",
    "subject": "physics",
    "difficulty": "medium",
    "type": "fill_blank"
  },
  {
    "id": "iit-jee-main-physics-medium-fill_blank-043",
    "question": "Fill in the blank: rate of change of velocity. The term is ____.",
    "options": [],
    "answer": "acceleration",
    "explanation": "Acceleration means rate of change of velocity.",
    "level": "iit-jee-main",
    "subject": "physics",
    "difficulty": "medium",
    "type": "fill_blank"
  },
  {
    "id": "iit-jee-main-physics-medium-fill_blank-044",
    "question": "The correct term for 'a push or pull that can change motion' is ____.",
    "options": [],
    "answer": "force",
    "explanation": "Force means a push or pull that can change motion.",
    "level": "iit-jee-main",
    "subject": "physics",
    "difficulty": "medium",
    "type": "fill_blank"
  },
  {
    "id": "iit-jee-main-physics-medium-fill_blank-045",
    "question": "____ means force multiplied by displacement in the direction of force.",
    "options": [],
    "answer": "work",
    "explanation": "Work means force multiplied by displacement in the direction of force.",
    "level": "iit-jee-main",
    "subject": "physics",
    "difficulty": "medium",
    "type": "fill_blank"
  },
  {
    "id": "iit-jee-main-physics-medium-fill_blank-046",
    "question": "Fill in the blank: rate of doing work. The term is ____.",
    "options": [],
    "answer": "power",
    "explanation": "Power means rate of doing work.",
    "level": "iit-jee-main",
    "subject": "physics",
    "difficulty": "medium",
    "type": "fill_blank"
  },
  {
    "id": "iit-jee-main-physics-medium-fill_blank-047",
    "question": "The correct term for 'mass multiplied by velocity' is ____.",
    "options": [],
    "answer": "momentum",
    "explanation": "Momentum means mass multiplied by velocity.",
    "level": "iit-jee-main",
    "subject": "physics",
    "difficulty": "medium",
    "type": "fill_blank"
  },
  {
    "id": "iit-jee-main-physics-medium-fill_blank-048",
    "question": "____ means the force of attraction between masses.",
    "options": [],
    "answer": "gravity",
    "explanation": "Gravity means the force of attraction between masses.",
    "level": "iit-jee-main",
    "subject": "physics",
    "difficulty": "medium",
    "type": "fill_blank"
  },
  {
    "id": "iit-jee-main-physics-medium-fill_blank-049",
    "question": "Fill in the blank: a force that opposes motion between surfaces. The term is ____.",
    "options": [],
    "answer": "friction",
    "explanation": "Friction means a force that opposes motion between surfaces.",
    "level": "iit-jee-main",
    "subject": "physics",
    "difficulty": "medium",
    "type": "fill_blank"
  },
  {
    "id": "iit-jee-main-physics-medium-fill_blank-050",
    "question": "The correct term for 'force per unit area' is ____.",
    "options": [],
    "answer": "pressure",
    "explanation": "Pressure means force per unit area.",
    "level": "iit-jee-main",
    "subject": "physics",
    "difficulty": "medium",
    "type": "fill_blank"
  }
]